TALENT/__init__.py
TALENT/configs/classical_configs.json
TALENT/configs/deep_configs.json
TALENT/configs/default/LinearRegression.json
TALENT/configs/default/LogReg.json
TALENT/configs/default/NCM.json
TALENT/configs/default/NaiveBayes.json
TALENT/configs/default/PFN-v2.json
TALENT/configs/default/RandomForest.json
TALENT/configs/default/amformer.json
TALENT/configs/default/autoint.json
TALENT/configs/default/bishop.json
TALENT/configs/default/catboost.json
TALENT/configs/default/danets.json
TALENT/configs/default/dcn2.json
TALENT/configs/default/dnnr.json
TALENT/configs/default/dummy.json
TALENT/configs/default/excelformer.json
TALENT/configs/default/ftt.json
TALENT/configs/default/grande.json
TALENT/configs/default/grownet.json
TALENT/configs/default/hyperfast.json
TALENT/configs/default/knn.json
TALENT/configs/default/lightgbm.json
TALENT/configs/default/linear.json
TALENT/configs/default/mlp.json
TALENT/configs/default/mlp_plr.json
TALENT/configs/default/modernNCA.json
TALENT/configs/default/node.json
TALENT/configs/default/protogate.json
TALENT/configs/default/ptarl.json
TALENT/configs/default/realmlp.json
TALENT/configs/default/resnet.json
TALENT/configs/default/saint.json
TALENT/configs/default/snn.json
TALENT/configs/default/svm.json
TALENT/configs/default/switchtab.json
TALENT/configs/default/t2gformer.json
TALENT/configs/default/tabcaps.json
TALENT/configs/default/tabm.json
TALENT/configs/default/tabnet.json
TALENT/configs/default/tabpfn.json
TALENT/configs/default/tabptm.json
TALENT/configs/default/tabr.json
TALENT/configs/default/tabtransformer.json
TALENT/configs/default/tangos.json
TALENT/configs/default/trompt.json
TALENT/configs/default/xgboost.json
TALENT/configs/opt_space/LinearRegression.json
TALENT/configs/opt_space/LogReg.json
TALENT/configs/opt_space/NCM.json
TALENT/configs/opt_space/NaiveBayes.json
TALENT/configs/opt_space/PFN-v2.json
TALENT/configs/opt_space/RandomForest.json
TALENT/configs/opt_space/amformer.json
TALENT_PyTorch-0.0.1.dist-info/LICENSE
TALENT_PyTorch-0.0.1.dist-info/METADATA
TALENT_PyTorch-0.0.1.dist-info/WHEEL
TALENT_PyTorch-0.0.1.dist-info/top_level.txt
TALENT_PyTorch-0.0.1.dist-info/RECORD
