Metadata-Version: 2.1
Name: TALENT-PyTorch
Version: 0.0.1
Summary: TALENT: A Tabular Analytics and Learning Toolbox
Home-page: https://github.com/qile2000/LAMDA-TALENT/tree/talent-pip
Author: TALENT Contributors from LAMDA-Tabular Group
Author-email: Siyang Liu <lsy00043@gmail.com>
Keywords: pytorch tabular deep learning machine learning
Requires-Python: ==3.10
License-File: LICENSE
Requires-Dist: tqdm (==4.66.4)
Requires-Dist: category-encoders (==2.6.3)
Requires-Dist: delu (==0.0.23)
Requires-Dist: einops (==0.8.0)
Requires-Dist: numpy (==1.26.4)
Requires-Dist: optuna (==3.6.1)
Requires-Dist: pandas (==2.2.2)
Requires-Dist: qhoptim (==1.1.0)
Requires-Dist: Requests (==2.31.0)
Requires-Dist: scikit-learn (==1.4.2)
Requires-Dist: scipy (==1.13.0)
Requires-Dist: torch (==2.0.1)
